guardian_ai/__init__.py
guardian_ai/cli.py
guardian_ai/guardian.py
guardian_ai-0.1.0.dist-info/METADATA
guardian_ai-0.1.0.dist-info/WHEEL
guardian_ai-0.1.0.dist-info/entry_points.txt
guardian_ai-0.1.0.dist-info/RECORD
